[
  {
    "Team": "D.C. Everest",
    "Division": "1",
    "Region": "1",
    "WIAASeed": 1,
    "BBMISeed": 14,
    "Seed": 1,
    "slug": "dc-everest",
    "RegionalSemis": 1.0,
    "RegionalChampion": 0.976,
    "SectionalSemiFinalist": 0.5853333333333334,
    "SectionalFinalist": 0.17533333333333334,
    "StateQualifier": 0.05333333333333334,
    "StateFinalist": 0.008,
    "StateChampion": 0.004
  },
  {
    "Team": "Appleton North",
    "Division": "1",
    "Region": "1",
    "WIAASeed": 2,
    "BBMISeed": 4,
    "Seed": 2,
    "slug": "appleton-north",
    "RegionalSemis": 1.0,
    "RegionalChampion": 0.9886666666666667,
    "SectionalSemiFinalist": 0.7986666666666666,
    "SectionalFinalist": 0.606,
    "StateQualifier": 0.4166666666666667,
    "StateFinalist": 0.23533333333333334,
    "StateChampion": 0.12133333333333333
  },
  {
    "Team": "Marshfield",
    "Division": "1",
    "Region": "1",
    "WIAASeed": 3,
    "BBMISeed": 11,
    "Seed": 3,
    "slug": "marshfield",
    "RegionalSemis": 1.0,
    "RegionalChampion": 0.9733333333333334,
    "SectionalSemiFinalist": 0.5266666666666666,
    "SectionalFinalist": 0.186,
    "StateQualifier": 0.108,
    "StateFinalist": 0.024,
    "StateChampion": 0.010666666666666666
  },
  {
    "Team": "Kaukauna",
    "Division": "1",
    "Region": "1",
    "WIAASeed": 4,
    "BBMISeed": 5,
    "Seed": 4,
    "slug": "kaukauna",
    "RegionalSemis": 1.0,
    "RegionalChampion": 0.9666666666666667,
    "SectionalSemiFinalist": 0.7073333333333334,
    "SectionalFinalist": 0.5546666666666666,
    "StateQualifier": 0.25466666666666665,
    "StateFinalist": 0.132,
    "StateChampion": 0.06066666666666667
  },
  {
    "Team": "Stevens Point",
    "Division": "1",
    "Region": "1",
    "WIAASeed": 5,
    "BBMISeed": 17,
    "Seed": 5,
    "slug": "stevens-point",
    "RegionalSemis": 1.0,
    "RegionalChampion": 0.9486666666666667,
    "SectionalSemiFinalist": 0.2853333333333333,
    "SectionalFinalist": 0.19866666666666666,
    "StateQualifier": 0.06133333333333333,
    "StateFinalist": 0.006666666666666667,
    "StateChampion": 0.0026666666666666666
  },
  {
    "Team": "Superior",
    "Division": "1",
    "Region": "1",
    "WIAASeed": 6,
    "BBMISeed": 20,
    "Seed": 6,
    "slug": "superior",
    "RegionalSemis": 1.0,
    "RegionalChampion": 0.9753333333333334,
    "SectionalSemiFinalist": 0.4706666666666667,
    "SectionalFinalist": 0.12333333333333334,
    "StateQualifier": 0.059333333333333335,
    "StateFinalist": 0.004666666666666667,
    "StateChampion": 0.0013333333333333333
  },
  {
    "Team": "Kimberly",
    "Division": "1",
    "Region": "1",
    "WIAASeed": 7,
    "BBMISeed": 19,
    "Seed": 7,
    "slug": "kimberly",
    "RegionalSemis": 1.0,
    "RegionalChampion": 0.8973333333333333,
    "SectionalSemiFinalist": 0.192,
    "SectionalFinalist": 0.084,
    "StateQualifier": 0.03266666666666666,
    "StateFinalist": 0.002,
    "StateChampion": 0.0
  },
  {
    "Team": "Hudson",
    "Division": "1",
    "Region": "1",
    "WIAASeed": 8,
    "BBMISeed": 39,
    "Seed": 8,
    "slug": "hudson",
    "RegionalSemis": 1.0,
    "RegionalChampion": 0.49466666666666664,
    "SectionalSemiFinalist": 0.16333333333333333,
    "SectionalFinalist": 0.024666666666666667,
    "StateQualifier": 0.004,
    "StateFinalist": 0.0,
    "StateChampion": 0.0
  },
  {
    "Team": "Neenah",
    "Division": "1",
    "Region": "1",
    "WIAASeed": 9,
    "BBMISeed": 23,
    "Seed": 9,
    "slug": "neenah",
    "RegionalSemis": 1.0,
    "RegionalChampion": 0.5053333333333333,
    "SectionalSemiFinalist": 0.24933333333333332,
    "SectionalFinalist": 0.046,
    "StateQualifier": 0.01,
    "StateFinalist": 0.0,
    "StateChampion": 0.0
  },
  {
    "Team": "Holmen",
    "Division": "1",
    "Region": "1",
    "WIAASeed": 10,
    "BBMISeed": 45,
    "Seed": 10,
    "slug": "holmen",
    "RegionalSemis": 1.0,
    "RegionalChampion": 0.10266666666666667,
    "SectionalSemiFinalist": 0.006666666666666667,
    "SectionalFinalist": 0.0006666666666666666,
    "StateQualifier": 0.0,
    "StateFinalist": 0.0,
    "StateChampion": 0.0
  },
  {
    "Team": "Wausau West",
    "Division": "1",
    "Region": "1",
    "WIAASeed": 11,
    "BBMISeed": 55,
    "Seed": 11,
    "slug": "wausau-west",
    "RegionalSemis": 1.0,
    "RegionalChampion": 0.024666666666666667,
    "SectionalSemiFinalist": 0.0026666666666666666,
    "SectionalFinalist": 0.0,
    "StateQualifier": 0.0,
    "StateFinalist": 0.0,
    "StateChampion": 0.0
  },
  {
    "Team": "Eau Claire Memorial",
    "Division": "1",
    "Region": "1",
    "WIAASeed": 12,
    "BBMISeed": 59,
    "Seed": 12,
    "slug": "eau-claire-memorial",
    "RegionalSemis": 1.0,
    "RegionalChampion": 0.051333333333333335,
    "SectionalSemiFinalist": 0.0033333333333333335,
    "SectionalFinalist": 0.0006666666666666666,
    "StateQualifier": 0.0,
    "StateFinalist": 0.0,
    "StateChampion": 0.0
  },
  {
    "Team": "Eau Claire North",
    "Division": "1",
    "Region": "1",
    "WIAASeed": 13,
    "BBMISeed": 56,
    "Seed": 13,
    "slug": "eau-claire-north",
    "RegionalSemis": 1.0,
    "RegionalChampion": 0.03333333333333333,
    "SectionalSemiFinalist": 0.004,
    "SectionalFinalist": 0.0,
    "StateQualifier": 0.0,
    "StateFinalist": 0.0,
    "StateChampion": 0.0
  },
  {
    "Team": "Appleton West",
    "Division": "1",
    "Region": "1",
    "WIAASeed": 14,
    "BBMISeed": 63,
    "Seed": 14,
    "slug": "appleton-west",
    "RegionalSemis": 1.0,
    "RegionalChampion": 0.02666666666666667,
    "SectionalSemiFinalist": 0.0,
    "SectionalFinalist": 0.0,
    "StateQualifier": 0.0,
    "StateFinalist": 0.0,
    "StateChampion": 0.0
  },
  {
    "Team": "Hortonville",
    "Division": "1",
    "Region": "1",
    "WIAASeed": 15,
    "BBMISeed": 66,
    "Seed": 15,
    "slug": "hortonville",
    "RegionalSemis": 1.0,
    "RegionalChampion": 0.011333333333333334,
    "SectionalSemiFinalist": 0.0026666666666666666,
    "SectionalFinalist": 0.0,
    "StateQualifier": 0.0,
    "StateFinalist": 0.0,
    "StateChampion": 0.0
  },
  {
    "Team": "Wisconsin Rapids",
    "Division": "1",
    "Region": "1",
    "WIAASeed": 16,
    "BBMISeed": 68,
    "Seed": 16,
    "slug": "wisconsin-rapids",
    "RegionalSemis": 1.0,
    "RegionalChampion": 0.024,
    "SectionalSemiFinalist": 0.002,
    "SectionalFinalist": 0.0,
    "StateQualifier": 0.0,
    "StateFinalist": 0.0,
    "StateChampion": 0.0
  },
  {
    "Team": "De Pere",
    "Division": "1",
    "Region": "2",
    "WIAASeed": 1,
    "BBMISeed": 7,
    "Seed": 1,
    "slug": "de-pere",
    "RegionalSemis": 1.0,
    "RegionalChampion": 0.9746666666666667,
    "SectionalSemiFinalist": 0.7133333333333334,
    "SectionalFinalist": 0.552,
    "StateQualifier": 0.2833333333333333,
    "StateFinalist": 0.12266666666666666,
    "StateChampion": 0.05533333333333333
  },
  {
    "Team": "Arrowhead",
    "Division": "1",
    "Region": "2",
    "WIAASeed": 2,
    "BBMISeed": 12,
    "Seed": 2,
    "slug": "arrowhead",
    "RegionalSemis": 1.0,
    "RegionalChampion": 0.9413333333333334,
    "SectionalSemiFinalist": 0.55,
    "SectionalFinalist": 0.31266666666666665,
    "StateQualifier": 0.17066666666666666,
    "StateFinalist": 0.04666666666666667,
    "StateChampion": 0.015333333333333332
  },
  {
    "Team": "Brookfield East",
    "Division": "1",
    "Region": "2",
    "WIAASeed": 3,
    "BBMISeed": 10,
    "Seed": 3,
    "slug": "brookfield-east",
    "RegionalSemis": 1.0,
    "RegionalChampion": 0.9573333333333334,
    "SectionalSemiFinalist": 0.6793333333333333,
    "SectionalFinalist": 0.322,
    "StateQualifier": 0.22933333333333333,
    "StateFinalist": 0.082,
    "StateChampion": 0.028
  },
  {
    "Team": "Hartford",
    "Division": "1",
    "Region": "2",
    "WIAASeed": 4,
    "BBMISeed": 25,
    "Seed": 4,
    "slug": "hartford",
    "RegionalSemis": 1.0,
    "RegionalChampion": 0.768,
    "SectionalSemiFinalist": 0.46266666666666667,
    "SectionalFinalist": 0.15866666666666668,
    "StateQualifier": 0.04,
    "StateFinalist": 0.008,
    "StateChampion": 0.0013333333333333333
  },
  {
    "Team": "Germantown",
    "Division": "1",
    "Region": "2",
    "WIAASeed": 5,
    "BBMISeed": 26,
    "Seed": 5,
    "slug": "germantown",
    "RegionalSemis": 1.0,
    "RegionalChampion": 0.7406666666666667,
    "SectionalSemiFinalist": 0.39,
    "SectionalFinalist": 0.114,
    "StateQualifier": 0.026,
    "StateFinalist": 0.005333333333333333,
    "StateChampion": 0.0006666666666666666
  },
  {
    "Team": "Sheboygan North",
    "Division": "1",
    "Region": "2",
    "WIAASeed": 6,
    "BBMISeed": 29,
    "Seed": 6,
    "slug": "sheboygan-north",
    "RegionalSemis": 1.0,
    "RegionalChampion": 0.958,
    "SectionalSemiFinalist": 0.3006666666666667,
    "SectionalFinalist": 0.08133333333333333,
    "StateQualifier": 0.036,
    "StateFinalist": 0.009333333333333334,
    "StateChampion": 0.0013333333333333333
  },
  {
    "Team": "Bay Port",
    "Division": "1",
    "Region": "2",
    "WIAASeed": 7,
    "BBMISeed": 13,
    "Seed": 7,
    "slug": "bay-port",
    "RegionalSemis": 1.0,
    "RegionalChampion": 0.6633333333333333,
    "SectionalSemiFinalist": 0.29533333333333334,
    "SectionalFinalist": 0.186,
    "StateQualifier": 0.11133333333333334,
    "StateFinalist": 0.03266666666666666,
    "StateChampion": 0.014
  },
  {
    "Team": "Menomonee Falls",
    "Division": "1",
    "Region": "2",
    "WIAASeed": 8,
    "BBMISeed": 28,
    "Seed": 8,
    "slug": "menomonee-falls",
    "RegionalSemis": 1.0,
    "RegionalChampion": 0.476,
    "SectionalSemiFinalist": 0.12266666666666666,
    "SectionalFinalist": 0.06266666666666666,
    "StateQualifier": 0.016666666666666666,
    "StateFinalist": 0.0033333333333333335,
    "StateChampion": 0.0
  },
  {
    "Team": "Homestead",
    "Division": "1",
    "Region": "2",
    "WIAASeed": 9,
    "BBMISeed": 21,
    "Seed": 9,
    "slug": "homestead",
    "RegionalSemis": 1.0,
    "RegionalChampion": 0.524,
    "SectionalSemiFinalist": 0.15866666666666668,
    "SectionalFinalist": 0.094,
    "StateQualifier": 0.028,
    "StateFinalist": 0.006,
    "StateChampion": 0.0
  },
  {
    "Team": "Oshkosh North",
    "Division": "1",
    "Region": "2",
    "WIAASeed": 10,
    "BBMISeed": 16,
    "Seed": 10,
    "slug": "oshkosh-north",
    "RegionalSemis": 1.0,
    "RegionalChampion": 0.33666666666666667,
    "SectionalSemiFinalist": 0.14933333333333335,
    "SectionalFinalist": 0.09533333333333334,
    "StateQualifier": 0.056,
    "StateFinalist": 0.015333333333333332,
    "StateChampion": 0.004666666666666667
  },
  {
    "Team": "Pewaukee",
    "Division": "1",
    "Region": "2",
    "WIAASeed": 11,
    "BBMISeed": 41,
    "Seed": 11,
    "slug": "pewaukee",
    "RegionalSemis": 1.0,
    "RegionalChampion": 0.042,
    "SectionalSemiFinalist": 0.010666666666666666,
    "SectionalFinalist": 0.0006666666666666666,
    "StateQualifier": 0.0006666666666666666,
    "StateFinalist": 0.0,
    "StateChampion": 0.0
  },
  {
    "Team": "Green Bay Preble",
    "Division": "1",
    "Region": "2",
    "WIAASeed": 12,
    "BBMISeed": 52,
    "Seed": 12,
    "slug": "green-bay-preble",
    "RegionalSemis": 1.0,
    "RegionalChampion": 0.25933333333333336,
    "SectionalSemiFinalist": 0.07133333333333333,
    "SectionalFinalist": 0.01,
    "StateQualifier": 0.0013333333333333333,
    "StateFinalist": 0.0,
    "StateChampion": 0.0
  },
  {
    "Team": "Fond Du Lac",
    "Division": "1",
    "Region": "2",
    "WIAASeed": 13,
    "BBMISeed": 49,
    "Seed": 13,
    "slug": "fond-du-lac",
    "RegionalSemis": 1.0,
    "RegionalChampion": 0.232,
    "SectionalSemiFinalist": 0.076,
    "SectionalFinalist": 0.008,
    "StateQualifier": 0.0006666666666666666,
    "StateFinalist": 0.0,
    "StateChampion": 0.0
  },
  {
    "Team": "Oshkosh West",
    "Division": "1",
    "Region": "2",
    "WIAASeed": 14,
    "BBMISeed": 50,
    "Seed": 14,
    "slug": "oshkosh-west",
    "RegionalSemis": 1.0,
    "RegionalChampion": 0.042666666666666665,
    "SectionalSemiFinalist": 0.009333333333333334,
    "SectionalFinalist": 0.0006666666666666666,
    "StateQualifier": 0.0,
    "StateFinalist": 0.0,
    "StateChampion": 0.0
  },
  {
    "Team": "Hamilton",
    "Division": "1",
    "Region": "2",
    "WIAASeed": 15,
    "BBMISeed": 57,
    "Seed": 15,
    "slug": "hamilton",
    "RegionalSemis": 1.0,
    "RegionalChampion": 0.058666666666666666,
    "SectionalSemiFinalist": 0.005333333333333333,
    "SectionalFinalist": 0.0013333333333333333,
    "StateQualifier": 0.0,
    "StateFinalist": 0.0,
    "StateChampion": 0.0
  },
  {
    "Team": "Manitowoc Lincoln",
    "Division": "1",
    "Region": "2",
    "WIAASeed": 16,
    "BBMISeed": 58,
    "Seed": 16,
    "slug": "manitowoc-lincoln",
    "RegionalSemis": 1.0,
    "RegionalChampion": 0.025333333333333333,
    "SectionalSemiFinalist": 0.005333333333333333,
    "SectionalFinalist": 0.0006666666666666666,
    "StateQualifier": 0.0,
    "StateFinalist": 0.0,
    "StateChampion": 0.0
  },
  {
    "Team": "Madison Memorial",
    "Division": "1",
    "Region": "3",
    "WIAASeed": 1,
    "BBMISeed": 3,
    "Seed": 1,
    "slug": "madison-memorial",
    "RegionalSemis": 1.0,
    "RegionalChampion": 0.9966666666666667,
    "SectionalSemiFinalist": 0.7886666666666666,
    "SectionalFinalist": 0.496,
    "StateQualifier": 0.214,
    "StateFinalist": 0.14066666666666666,
    "StateChampion": 0.07
  },
  {
    "Team": "Beloit Memorial",
    "Division": "1",
    "Region": "3",
    "WIAASeed": 2,
    "BBMISeed": 8,
    "Seed": 2,
    "slug": "beloit-memorial",
    "RegionalSemis": 1.0,
    "RegionalChampion": 0.978,
    "SectionalSemiFinalist": 0.848,
    "SectionalFinalist": 0.5733333333333334,
    "StateQualifier": 0.39266666666666666,
    "StateFinalist": 0.20733333333333334,
    "StateChampion": 0.12
  },
  {
    "Team": "Verona",
    "Division": "1",
    "Region": "3",
    "WIAASeed": 3,
    "BBMISeed": 2,
    "Seed": 3,
    "slug": "verona",
    "RegionalSemis": 1.0,
    "RegionalChampion": 0.9266666666666666,
    "SectionalSemiFinalist": 0.78,
    "SectionalFinalist": 0.346,
    "StateQualifier": 0.24866666666666667,
    "StateFinalist": 0.17733333333333334,
    "StateChampion": 0.08133333333333333
  },
  {
    "Team": "Waunakee",
    "Division": "1",
    "Region": "3",
    "WIAASeed": 4,
    "BBMISeed": 15,
    "Seed": 4,
    "slug": "waunakee",
    "RegionalSemis": 1.0,
    "RegionalChampion": 0.852,
    "SectionalSemiFinalist": 0.4066666666666667,
    "SectionalFinalist": 0.15266666666666667,
    "StateQualifier": 0.03933333333333333,
    "StateFinalist": 0.014,
    "StateChampion": 0.005333333333333333
  },
  {
    "Team": "Middleton",
    "Division": "1",
    "Region": "3",
    "WIAASeed": 5,
    "BBMISeed": 9,
    "Seed": 5,
    "slug": "middleton",
    "RegionalSemis": 1.0,
    "RegionalChampion": 0.8353333333333334,
    "SectionalSemiFinalist": 0.52,
    "SectionalFinalist": 0.2806666666666667,
    "StateQualifier": 0.076,
    "StateFinalist": 0.03,
    "StateChampion": 0.012666666666666666
  },
  {
    "Team": "Oregon",
    "Division": "1",
    "Region": "3",
    "WIAASeed": 6,
    "BBMISeed": 30,
    "Seed": 6,
    "slug": "oregon",
    "RegionalSemis": 1.0,
    "RegionalChampion": 0.9373333333333334,
    "SectionalSemiFinalist": 0.17733333333333334,
    "SectionalFinalist": 0.024666666666666667,
    "StateQualifier": 0.006,
    "StateFinalist": 0.0006666666666666666,
    "StateChampion": 0.0006666666666666666
  },
  {
    "Team": "Monona Grove",
    "Division": "1",
    "Region": "3",
    "WIAASeed": 7,
    "BBMISeed": 27,
    "Seed": 7,
    "slug": "monona-grove",
    "RegionalSemis": 1.0,
    "RegionalChampion": 0.5333333333333333,
    "SectionalSemiFinalist": 0.066,
    "SectionalFinalist": 0.020666666666666667,
    "StateQualifier": 0.005333333333333333,
    "StateFinalist": 0.0013333333333333333,
    "StateChampion": 0.0
  },
  {
    "Team": "Kettle Moraine",
    "Division": "1",
    "Region": "3",
    "WIAASeed": 8,
    "BBMISeed": 24,
    "Seed": 8,
    "slug": "kettle-moraine",
    "RegionalSemis": 1.0,
    "RegionalChampion": 0.5673333333333334,
    "SectionalSemiFinalist": 0.09933333333333333,
    "SectionalFinalist": 0.029333333333333333,
    "StateQualifier": 0.005333333333333333,
    "StateFinalist": 0.0013333333333333333,
    "StateChampion": 0.0
  },
  {
    "Team": "Badger",
    "Division": "1",
    "Region": "3",
    "WIAASeed": 9,
    "BBMISeed": 32,
    "Seed": 9,
    "slug": "badger",
    "RegionalSemis": 1.0,
    "RegionalChampion": 0.43266666666666664,
    "SectionalSemiFinalist": 0.11133333333333334,
    "SectionalFinalist": 0.02666666666666667,
    "StateQualifier": 0.0026666666666666666,
    "StateFinalist": 0.0,
    "StateChampion": 0.0
  },
  {
    "Team": "Madison La Follette",
    "Division": "1",
    "Region": "3",
    "WIAASeed": 10,
    "BBMISeed": 18,
    "Seed": 10,
    "slug": "madison-la-follette",
    "RegionalSemis": 1.0,
    "RegionalChampion": 0.4666666666666667,
    "SectionalSemiFinalist": 0.08066666666666666,
    "SectionalFinalist": 0.028,
    "StateQualifier": 0.008,
    "StateFinalist": 0.0033333333333333335,
    "StateChampion": 0.0013333333333333333
  },
  {
    "Team": "Madison West",
    "Division": "1",
    "Region": "3",
    "WIAASeed": 11,
    "BBMISeed": 33,
    "Seed": 11,
    "slug": "madison-west",
    "RegionalSemis": 1.0,
    "RegionalChampion": 0.06266666666666666,
    "SectionalSemiFinalist": 0.010666666666666666,
    "SectionalFinalist": 0.0026666666666666666,
    "StateQualifier": 0.0006666666666666666,
    "StateFinalist": 0.0006666666666666666,
    "StateChampion": 0.0
  },
  {
    "Team": "Janesville Craig",
    "Division": "1",
    "Region": "3",
    "WIAASeed": 12,
    "BBMISeed": 31,
    "Seed": 12,
    "slug": "janesville-craig",
    "RegionalSemis": 1.0,
    "RegionalChampion": 0.16466666666666666,
    "SectionalSemiFinalist": 0.050666666666666665,
    "SectionalFinalist": 0.012666666666666666,
    "StateQualifier": 0.0013333333333333333,
    "StateFinalist": 0.0,
    "StateChampion": 0.0
  },
  {
    "Team": "Mukwonago",
    "Division": "1",
    "Region": "3",
    "WIAASeed": 13,
    "BBMISeed": 47,
    "Seed": 13,
    "slug": "mukwonago",
    "RegionalSemis": 1.0,
    "RegionalChampion": 0.148,
    "SectionalSemiFinalist": 0.02266666666666667,
    "SectionalFinalist": 0.002,
    "StateQualifier": 0.0,
    "StateFinalist": 0.0,
    "StateChampion": 0.0
  },
  {
    "Team": "Sun Prairie West",
    "Division": "1",
    "Region": "3",
    "WIAASeed": 14,
    "BBMISeed": 35,
    "Seed": 14,
    "slug": "sun-prairie-west",
    "RegionalSemis": 1.0,
    "RegionalChampion": 0.07333333333333333,
    "SectionalSemiFinalist": 0.032,
    "SectionalFinalist": 0.004,
    "StateQualifier": 0.0,
    "StateFinalist": 0.0,
    "StateChampion": 0.0
  },
  {
    "Team": "Madison East",
    "Division": "1",
    "Region": "3",
    "WIAASeed": 15,
    "BBMISeed": 53,
    "Seed": 15,
    "slug": "madison-east",
    "RegionalSemis": 1.0,
    "RegionalChampion": 0.022,
    "SectionalSemiFinalist": 0.005333333333333333,
    "SectionalFinalist": 0.0006666666666666666,
    "StateQualifier": 0.0,
    "StateFinalist": 0.0,
    "StateChampion": 0.0
  },
  {
    "Team": "Westosha Central",
    "Division": "1",
    "Region": "3",
    "WIAASeed": 16,
    "BBMISeed": 64,
    "Seed": 16,
    "slug": "westosha-central",
    "RegionalSemis": 1.0,
    "RegionalChampion": 0.0033333333333333335,
    "SectionalSemiFinalist": 0.0006666666666666666,
    "SectionalFinalist": 0.0,
    "StateQualifier": 0.0,
    "StateFinalist": 0.0,
    "StateChampion": 0.0
  },
  {
    "Team": "Wisconsin Lutheran",
    "Division": "1",
    "Region": "4",
    "WIAASeed": 1,
    "BBMISeed": 1,
    "Seed": 1,
    "slug": "wisconsin-lutheran",
    "RegionalSemis": 1.0,
    "RegionalChampion": 0.9986666666666667,
    "SectionalSemiFinalist": 0.9186666666666666,
    "SectionalFinalist": 0.8333333333333334,
    "StateQualifier": 0.438,
    "StateFinalist": 0.35933333333333334,
    "StateChampion": 0.194
  },
  {
    "Team": "West Allis Central",
    "Division": "1",
    "Region": "4",
    "WIAASeed": 2,
    "BBMISeed": 6,
    "Seed": 2,
    "slug": "west-allis-central",
    "RegionalSemis": 1.0,
    "RegionalChampion": 0.9726666666666667,
    "SectionalSemiFinalist": 0.904,
    "SectionalFinalist": 0.798,
    "StateQualifier": 0.48933333333333334,
    "StateFinalist": 0.306,
    "StateChampion": 0.19
  },
  {
    "Team": "Racine Case",
    "Division": "1",
    "Region": "4",
    "WIAASeed": 3,
    "BBMISeed": 22,
    "Seed": 3,
    "slug": "racine-case",
    "RegionalSemis": 1.0,
    "RegionalChampion": 0.85,
    "SectionalSemiFinalist": 0.5653333333333334,
    "SectionalFinalist": 0.11466666666666667,
    "StateQualifier": 0.03933333333333333,
    "StateFinalist": 0.01,
    "StateChampion": 0.0033333333333333335
  },
  {
    "Team": "Milwaukee Hamilton",
    "Division": "1",
    "Region": "4",
    "WIAASeed": 4,
    "BBMISeed": 40,
    "Seed": 4,
    "slug": "milwaukee-hamilton",
    "RegionalSemis": 1.0,
    "RegionalChampion": 0.7726666666666666,
    "SectionalSemiFinalist": 0.498,
    "SectionalFinalist": 0.07533333333333334,
    "StateQualifier": 0.008,
    "StateFinalist": 0.0013333333333333333,
    "StateChampion": 0.0
  },
  {
    "Team": "Franklin",
    "Division": "1",
    "Region": "4",
    "WIAASeed": 5,
    "BBMISeed": 44,
    "Seed": 5,
    "slug": "franklin",
    "RegionalSemis": 1.0,
    "RegionalChampion": 0.4686666666666667,
    "SectionalSemiFinalist": 0.19066666666666668,
    "SectionalFinalist": 0.028666666666666667,
    "StateQualifier": 0.004,
    "StateFinalist": 0.002,
    "StateChampion": 0.0
  },
  {
    "Team": "Kenosha Bradford",
    "Division": "1",
    "Region": "4",
    "WIAASeed": 6,
    "BBMISeed": 36,
    "Seed": 6,
    "slug": "kenosha-bradford",
    "RegionalSemis": 1.0,
    "RegionalChampion": 0.8706666666666667,
    "SectionalSemiFinalist": 0.3406666666666667,
    "SectionalFinalist": 0.04133333333333333,
    "StateQualifier": 0.008666666666666666,
    "StateFinalist": 0.0006666666666666666,
    "StateChampion": 0.0
  },
  {
    "Team": "Racine Park",
    "Division": "1",
    "Region": "4",
    "WIAASeed": 7,
    "BBMISeed": 34,
    "Seed": 7,
    "slug": "racine-park",
    "RegionalSemis": 1.0,
    "RegionalChampion": 0.626,
    "SectionalSemiFinalist": 0.05466666666666667,
    "SectionalFinalist": 0.026,
    "StateQualifier": 0.004666666666666667,
    "StateFinalist": 0.0,
    "StateChampion": 0.0
  },
  {
    "Team": "Oak Creek",
    "Division": "1",
    "Region": "4",
    "WIAASeed": 8,
    "BBMISeed": 37,
    "Seed": 8,
    "slug": "oak-creek",
    "RegionalSemis": 1.0,
    "RegionalChampion": 0.554,
    "SectionalSemiFinalist": 0.04533333333333334,
    "SectionalFinalist": 0.017333333333333333,
    "StateQualifier": 0.0006666666666666666,
    "StateFinalist": 0.0,
    "StateChampion": 0.0
  },
  {
    "Team": "Marquette University",
    "Division": "1",
    "Region": "4",
    "WIAASeed": 9,
    "BBMISeed": 42,
    "Seed": 9,
    "slug": "marquette-university",
    "RegionalSemis": 1.0,
    "RegionalChampion": 0.446,
    "SectionalSemiFinalist": 0.036,
    "SectionalFinalist": 0.016,
    "StateQualifier": 0.002,
    "StateFinalist": 0.0,
    "StateChampion": 0.0
  },
  {
    "Team": "Muskego",
    "Division": "1",
    "Region": "4",
    "WIAASeed": 10,
    "BBMISeed": 43,
    "Seed": 10,
    "slug": "muskego",
    "RegionalSemis": 1.0,
    "RegionalChampion": 0.374,
    "SectionalSemiFinalist": 0.025333333333333333,
    "SectionalFinalist": 0.008666666666666666,
    "StateQualifier": 0.0006666666666666666,
    "StateFinalist": 0.0,
    "StateChampion": 0.0
  },
  {
    "Team": "Milwaukee Riverside",
    "Division": "1",
    "Region": "4",
    "WIAASeed": 11,
    "BBMISeed": 46,
    "Seed": 11,
    "slug": "milwaukee-riverside",
    "RegionalSemis": 1.0,
    "RegionalChampion": 0.12933333333333333,
    "SectionalSemiFinalist": 0.032,
    "SectionalFinalist": 0.002,
    "StateQualifier": 0.0,
    "StateFinalist": 0.0,
    "StateChampion": 0.0
  },
  {
    "Team": "Milwaukee South",
    "Division": "1",
    "Region": "4",
    "WIAASeed": 12,
    "BBMISeed": 38,
    "Seed": 12,
    "slug": "milwaukee-south",
    "RegionalSemis": 1.0,
    "RegionalChampion": 0.5313333333333333,
    "SectionalSemiFinalist": 0.23933333333333334,
    "SectionalFinalist": 0.025333333333333333,
    "StateQualifier": 0.0026666666666666666,
    "StateFinalist": 0.0,
    "StateChampion": 0.0
  },
  {
    "Team": "Milwaukee King",
    "Division": "1",
    "Region": "4",
    "WIAASeed": 13,
    "BBMISeed": 54,
    "Seed": 13,
    "slug": "milwaukee-king",
    "RegionalSemis": 1.0,
    "RegionalChampion": 0.22733333333333333,
    "SectionalSemiFinalist": 0.072,
    "SectionalFinalist": 0.004,
    "StateQualifier": 0.0006666666666666666,
    "StateFinalist": 0.0,
    "StateChampion": 0.0
  },
  {
    "Team": "Milwaukee Reagan",
    "Division": "1",
    "Region": "4",
    "WIAASeed": 14,
    "BBMISeed": 48,
    "Seed": 14,
    "slug": "milwaukee-reagan",
    "RegionalSemis": 1.0,
    "RegionalChampion": 0.15,
    "SectionalSemiFinalist": 0.062,
    "SectionalFinalist": 0.004666666666666667,
    "StateQualifier": 0.0006666666666666666,
    "StateFinalist": 0.0,
    "StateChampion": 0.0
  },
  {
    "Team": "Milwaukee Pulaski/Carmen South/Carmen Southeast",
    "Division": "1",
    "Region": "4",
    "WIAASeed": 15,
    "BBMISeed": 51,
    "Seed": 15,
    "slug": "milwaukee-pulaski-carmen-south-carmen-southeast",
    "RegionalSemis": 1.0,
    "RegionalChampion": 0.027333333333333334,
    "SectionalSemiFinalist": 0.016,
    "SectionalFinalist": 0.004666666666666667,
    "StateQualifier": 0.0006666666666666666,
    "StateFinalist": 0.0,
    "StateChampion": 0.0
  },
  {
    "Team": "Kenosha Tremper",
    "Division": "1",
    "Region": "4",
    "WIAASeed": 16,
    "BBMISeed": 70,
    "Seed": 16,
    "slug": "kenosha-tremper",
    "RegionalSemis": 1.0,
    "RegionalChampion": 0.0013333333333333333,
    "SectionalSemiFinalist": 0.0,
    "SectionalFinalist": 0.0,
    "StateQualifier": 0.0,
    "StateFinalist": 0.0,
    "StateChampion": 0.0
  }
]