[
  {
    "Team": "Turtle Lake",
    "Division": "5",
    "Region": "1A",
    "WIAASeed": 1,
    "BBMISeed": 9,
    "Seed": 1,
    "slug": "turtle-lake",
    "RegionalSemis": 1.0,
    "RegionalChampion": 0.8816666666666667,
    "SectionalSemiFinalist": 0.545,
    "SectionalFinalist": 0.31166666666666665,
    "StateQualifier": 0.15833333333333333,
    "StateFinalist": 0.07666666666666666,
    "StateChampion": 0.035
  },
  {
    "Team": "Drummond",
    "Division": "5",
    "Region": "1A",
    "WIAASeed": 2,
    "BBMISeed": 18,
    "Seed": 2,
    "slug": "drummond",
    "RegionalSemis": 1.0,
    "RegionalChampion": 0.915,
    "SectionalSemiFinalist": 0.7116666666666667,
    "SectionalFinalist": 0.4275,
    "StateQualifier": 0.18666666666666668,
    "StateFinalist": 0.07,
    "StateChampion": 0.029166666666666667
  },
  {
    "Team": "Webster",
    "Division": "5",
    "Region": "1A",
    "WIAASeed": 3,
    "BBMISeed": 17,
    "Seed": 3,
    "slug": "webster",
    "RegionalSemis": 1.0,
    "RegionalChampion": 0.8983333333333333,
    "SectionalSemiFinalist": 0.2475,
    "SectionalFinalist": 0.1575,
    "StateQualifier": 0.050833333333333335,
    "StateFinalist": 0.020833333333333332,
    "StateChampion": 0.0075
  },
  {
    "Team": "Washburn",
    "Division": "5",
    "Region": "1A",
    "WIAASeed": 4,
    "BBMISeed": 23,
    "Seed": 4,
    "slug": "washburn",
    "RegionalSemis": 1.0,
    "RegionalChampion": 0.7633333333333333,
    "SectionalSemiFinalist": 0.35333333333333333,
    "SectionalFinalist": 0.0825,
    "StateQualifier": 0.019166666666666665,
    "StateFinalist": 0.0075,
    "StateChampion": 0.0033333333333333335
  },
  {
    "Team": "Frederic",
    "Division": "5",
    "Region": "1A",
    "WIAASeed": 5,
    "BBMISeed": 38,
    "Seed": 5,
    "slug": "frederic",
    "RegionalSemis": 1.0,
    "RegionalChampion": 0.23666666666666666,
    "SectionalSemiFinalist": 0.07416666666666667,
    "SectionalFinalist": 0.011666666666666667,
    "StateQualifier": 0.0025,
    "StateFinalist": 0.0008333333333333334,
    "StateChampion": 0.0008333333333333334
  },
  {
    "Team": "New Auburn",
    "Division": "5",
    "Region": "1A",
    "WIAASeed": 6,
    "BBMISeed": 41,
    "Seed": 6,
    "slug": "new-auburn",
    "RegionalSemis": 1.0,
    "RegionalChampion": 0.10166666666666667,
    "SectionalSemiFinalist": 0.014166666666666666,
    "SectionalFinalist": 0.005,
    "StateQualifier": 0.0,
    "StateFinalist": 0.0,
    "StateChampion": 0.0
  },
  {
    "Team": "Bruce",
    "Division": "5",
    "Region": "1A",
    "WIAASeed": 7,
    "BBMISeed": 60,
    "Seed": 7,
    "slug": "bruce",
    "RegionalSemis": 1.0,
    "RegionalChampion": 0.085,
    "SectionalSemiFinalist": 0.02666666666666667,
    "SectionalFinalist": 0.0033333333333333335,
    "StateQualifier": 0.0016666666666666668,
    "StateFinalist": 0.0008333333333333334,
    "StateChampion": 0.0
  },
  {
    "Team": "Solon Springs",
    "Division": "5",
    "Region": "1A",
    "WIAASeed": 8,
    "BBMISeed": 53,
    "Seed": 8,
    "slug": "solon-springs",
    "RegionalSemis": 1.0,
    "RegionalChampion": 0.11833333333333333,
    "SectionalSemiFinalist": 0.0275,
    "SectionalFinalist": 0.0008333333333333334,
    "StateQualifier": 0.0,
    "StateFinalist": 0.0,
    "StateChampion": 0.0
  },
  {
    "Team": "Loyal",
    "Division": "5",
    "Region": "1B",
    "WIAASeed": 1,
    "BBMISeed": 28,
    "Seed": 1,
    "slug": "loyal",
    "RegionalSemis": 1.0,
    "RegionalChampion": 0.775,
    "SectionalSemiFinalist": 0.27416666666666667,
    "SectionalFinalist": 0.095,
    "StateQualifier": 0.05416666666666667,
    "StateFinalist": 0.0125,
    "StateChampion": 0.0016666666666666668
  },
  {
    "Team": "Columbus Catholic",
    "Division": "5",
    "Region": "1B",
    "WIAASeed": 2,
    "BBMISeed": 19,
    "Seed": 2,
    "slug": "columbus-catholic",
    "RegionalSemis": 1.0,
    "RegionalChampion": 0.7666666666666667,
    "SectionalSemiFinalist": 0.43583333333333335,
    "SectionalFinalist": 0.2833333333333333,
    "StateQualifier": 0.145,
    "StateFinalist": 0.056666666666666664,
    "StateChampion": 0.020833333333333332
  },
  {
    "Team": "Prentice",
    "Division": "5",
    "Region": "1B",
    "WIAASeed": 3,
    "BBMISeed": 2,
    "Seed": 3,
    "slug": "prentice",
    "RegionalSemis": 1.0,
    "RegionalChampion": 0.9166666666666666,
    "SectionalSemiFinalist": 0.4716666666666667,
    "SectionalFinalist": 0.385,
    "StateQualifier": 0.2658333333333333,
    "StateFinalist": 0.15166666666666667,
    "StateChampion": 0.08666666666666667
  },
  {
    "Team": "Mellen",
    "Division": "5",
    "Region": "1B",
    "WIAASeed": 4,
    "BBMISeed": 12,
    "Seed": 4,
    "slug": "mellen",
    "RegionalSemis": 1.0,
    "RegionalChampion": 0.7358333333333333,
    "SectionalSemiFinalist": 0.5116666666666667,
    "SectionalFinalist": 0.13333333333333333,
    "StateQualifier": 0.06333333333333334,
    "StateFinalist": 0.03333333333333333,
    "StateChampion": 0.0125
  },
  {
    "Team": "Rib Lake",
    "Division": "5",
    "Region": "1B",
    "WIAASeed": 5,
    "BBMISeed": 8,
    "Seed": 5,
    "slug": "rib-lake",
    "RegionalSemis": 1.0,
    "RegionalChampion": 0.26416666666666666,
    "SectionalSemiFinalist": 0.17916666666666667,
    "SectionalFinalist": 0.06583333333333333,
    "StateQualifier": 0.035,
    "StateFinalist": 0.020833333333333332,
    "StateChampion": 0.009166666666666667
  },
  {
    "Team": "Flambeau",
    "Division": "5",
    "Region": "1B",
    "WIAASeed": 6,
    "BBMISeed": 29,
    "Seed": 6,
    "slug": "flambeau",
    "RegionalSemis": 1.0,
    "RegionalChampion": 0.08333333333333333,
    "SectionalSemiFinalist": 0.03333333333333333,
    "SectionalFinalist": 0.0125,
    "StateQualifier": 0.008333333333333333,
    "StateFinalist": 0.0008333333333333334,
    "StateChampion": 0.0008333333333333334
  },
  {
    "Team": "Athens",
    "Division": "5",
    "Region": "1B",
    "WIAASeed": 7,
    "BBMISeed": 26,
    "Seed": 7,
    "slug": "athens",
    "RegionalSemis": 1.0,
    "RegionalChampion": 0.23333333333333334,
    "SectionalSemiFinalist": 0.059166666666666666,
    "SectionalFinalist": 0.02,
    "StateQualifier": 0.0075,
    "StateFinalist": 0.0016666666666666668,
    "StateChampion": 0.0016666666666666668
  },
  {
    "Team": "Owen-Withee",
    "Division": "5",
    "Region": "1B",
    "WIAASeed": 8,
    "BBMISeed": 33,
    "Seed": 8,
    "slug": "owen-withee",
    "RegionalSemis": 1.0,
    "RegionalChampion": 0.225,
    "SectionalSemiFinalist": 0.035,
    "SectionalFinalist": 0.005,
    "StateQualifier": 0.0016666666666666668,
    "StateFinalist": 0.0008333333333333334,
    "StateChampion": 0.0008333333333333334
  },
  {
    "Team": "Tigerton",
    "Division": "5",
    "Region": "2A",
    "WIAASeed": 1,
    "BBMISeed": 11,
    "Seed": 1,
    "slug": "tigerton",
    "RegionalSemis": 1.0,
    "RegionalChampion": 0.9441666666666667,
    "SectionalSemiFinalist": 0.71,
    "SectionalFinalist": 0.4683333333333333,
    "StateQualifier": 0.2125,
    "StateFinalist": 0.10666666666666667,
    "StateChampion": 0.05583333333333333
  },
  {
    "Team": "Wabeno/Laona",
    "Division": "5",
    "Region": "2A",
    "WIAASeed": 2,
    "BBMISeed": 22,
    "Seed": 2,
    "slug": "wabeno-laona",
    "RegionalSemis": 1.0,
    "RegionalChampion": 0.8758333333333334,
    "SectionalSemiFinalist": 0.6916666666666667,
    "SectionalFinalist": 0.34,
    "StateQualifier": 0.085,
    "StateFinalist": 0.02666666666666667,
    "StateChampion": 0.01
  },
  {
    "Team": "Three Lakes",
    "Division": "5",
    "Region": "2A",
    "WIAASeed": 3,
    "BBMISeed": 44,
    "Seed": 3,
    "slug": "three-lakes",
    "RegionalSemis": 1.0,
    "RegionalChampion": 0.7475,
    "SectionalSemiFinalist": 0.215,
    "SectionalFinalist": 0.08666666666666667,
    "StateQualifier": 0.006666666666666667,
    "StateFinalist": 0.0,
    "StateChampion": 0.0
  },
  {
    "Team": "Pacelli",
    "Division": "5",
    "Region": "2A",
    "WIAASeed": 4,
    "BBMISeed": 72,
    "Seed": 4,
    "slug": "pacelli",
    "RegionalSemis": 1.0,
    "RegionalChampion": 0.35,
    "SectionalSemiFinalist": 0.06666666666666667,
    "SectionalFinalist": 0.0125,
    "StateQualifier": 0.0,
    "StateFinalist": 0.0,
    "StateChampion": 0.0
  },
  {
    "Team": "Newman Catholic",
    "Division": "5",
    "Region": "2A",
    "WIAASeed": 5,
    "BBMISeed": 46,
    "Seed": 5,
    "slug": "newman-catholic",
    "RegionalSemis": 1.0,
    "RegionalChampion": 0.65,
    "SectionalSemiFinalist": 0.19583333333333333,
    "SectionalFinalist": 0.055,
    "StateQualifier": 0.006666666666666667,
    "StateFinalist": 0.0016666666666666668,
    "StateChampion": 0.0
  },
  {
    "Team": "Rosholt",
    "Division": "5",
    "Region": "2A",
    "WIAASeed": 6,
    "BBMISeed": 55,
    "Seed": 6,
    "slug": "rosholt",
    "RegionalSemis": 1.0,
    "RegionalChampion": 0.2525,
    "SectionalSemiFinalist": 0.04416666666666667,
    "SectionalFinalist": 0.011666666666666667,
    "StateQualifier": 0.0,
    "StateFinalist": 0.0,
    "StateChampion": 0.0
  },
  {
    "Team": "Bowler",
    "Division": "5",
    "Region": "2A",
    "WIAASeed": 7,
    "BBMISeed": 69,
    "Seed": 7,
    "slug": "bowler",
    "RegionalSemis": 1.0,
    "RegionalChampion": 0.12416666666666666,
    "SectionalSemiFinalist": 0.049166666666666664,
    "SectionalFinalist": 0.020833333333333332,
    "StateQualifier": 0.0008333333333333334,
    "StateFinalist": 0.0,
    "StateChampion": 0.0
  },
  {
    "Team": "Tri-County",
    "Division": "5",
    "Region": "2A",
    "WIAASeed": 9,
    "BBMISeed": 67,
    "Seed": 8,
    "slug": "tri-county",
    "RegionalSemis": 1.0,
    "RegionalChampion": 0.05583333333333333,
    "SectionalSemiFinalist": 0.0275,
    "SectionalFinalist": 0.005,
    "StateQualifier": 0.0008333333333333334,
    "StateFinalist": 0.0,
    "StateChampion": 0.0
  },
  {
    "Team": "Reedsville",
    "Division": "5",
    "Region": "2B",
    "WIAASeed": 1,
    "BBMISeed": 1,
    "Seed": 1,
    "slug": "reedsville",
    "RegionalSemis": 1.0,
    "RegionalChampion": 0.95,
    "SectionalSemiFinalist": 0.8475,
    "SectionalFinalist": 0.665,
    "StateQualifier": 0.5258333333333334,
    "StateFinalist": 0.3541666666666667,
    "StateChampion": 0.20083333333333334
  },
  {
    "Team": "Elkhart Lake-Glenbeulah",
    "Division": "5",
    "Region": "2B",
    "WIAASeed": 2,
    "BBMISeed": 32,
    "Seed": 2,
    "slug": "elkhart-lake-glenbeulah",
    "RegionalSemis": 1.0,
    "RegionalChampion": 0.8858333333333334,
    "SectionalSemiFinalist": 0.7616666666666667,
    "SectionalFinalist": 0.2608333333333333,
    "StateQualifier": 0.13916666666666666,
    "StateFinalist": 0.04416666666666667,
    "StateChampion": 0.005833333333333334
  },
  {
    "Team": "Oneida Nation",
    "Division": "5",
    "Region": "2B",
    "WIAASeed": 3,
    "BBMISeed": 57,
    "Seed": 3,
    "slug": "oneida-nation",
    "RegionalSemis": 1.0,
    "RegionalChampion": 0.5533333333333333,
    "SectionalSemiFinalist": 0.0925,
    "SectionalFinalist": 0.015,
    "StateQualifier": 0.005,
    "StateFinalist": 0.0,
    "StateChampion": 0.0
  },
  {
    "Team": "Providence Academy (Green Bay)",
    "Division": "5",
    "Region": "2B",
    "WIAASeed": 4,
    "BBMISeed": 63,
    "Seed": 4,
    "slug": "providence-academy-green-bay",
    "RegionalSemis": 1.0,
    "RegionalChampion": 0.6183333333333333,
    "SectionalSemiFinalist": 0.0725,
    "SectionalFinalist": 0.011666666666666667,
    "StateQualifier": 0.004166666666666667,
    "StateFinalist": 0.0,
    "StateChampion": 0.0
  },
  {
    "Team": "Green Bay NEW Lutheran",
    "Division": "5",
    "Region": "2B",
    "WIAASeed": 6,
    "BBMISeed": 54,
    "Seed": 6,
    "slug": "green-bay-new-lutheran",
    "RegionalSemis": 1.0,
    "RegionalChampion": 0.44666666666666666,
    "SectionalSemiFinalist": 0.085,
    "SectionalFinalist": 0.019166666666666665,
    "StateQualifier": 0.005,
    "StateFinalist": 0.0008333333333333334,
    "StateChampion": 0.0
  },
  {
    "Team": "Hilbert",
    "Division": "5",
    "Region": "2B",
    "WIAASeed": 7,
    "BBMISeed": 51,
    "Seed": 7,
    "slug": "hilbert",
    "RegionalSemis": 1.0,
    "RegionalChampion": 0.11416666666666667,
    "SectionalSemiFinalist": 0.060833333333333336,
    "SectionalFinalist": 0.0175,
    "StateQualifier": 0.005,
    "StateFinalist": 0.0016666666666666668,
    "StateChampion": 0.0
  },
  {
    "Team": "Lourdes Academy",
    "Division": "5",
    "Region": "2B",
    "WIAASeed": 8,
    "BBMISeed": 31,
    "Seed": 8,
    "slug": "lourdes-academy",
    "RegionalSemis": 1.0,
    "RegionalChampion": 0.05,
    "SectionalSemiFinalist": 0.03916666666666667,
    "SectionalFinalist": 0.0075,
    "StateQualifier": 0.0016666666666666668,
    "StateFinalist": 0.0008333333333333334,
    "StateChampion": 0.0008333333333333334
  },
  {
    "Team": "Gibraltar",
    "Division": "5",
    "Region": "2B",
    "WIAASeed": 12,
    "BBMISeed": 80,
    "Seed": 5,
    "slug": "gibraltar",
    "RegionalSemis": 1.0,
    "RegionalChampion": 0.38166666666666665,
    "SectionalSemiFinalist": 0.04083333333333333,
    "SectionalFinalist": 0.0033333333333333335,
    "StateQualifier": 0.0016666666666666668,
    "StateFinalist": 0.0,
    "StateChampion": 0.0
  },
  {
    "Team": "Royall",
    "Division": "5",
    "Region": "3A",
    "WIAASeed": 1,
    "BBMISeed": 16,
    "Seed": 1,
    "slug": "royall",
    "RegionalSemis": 1.0,
    "RegionalChampion": 0.9133333333333333,
    "SectionalSemiFinalist": 0.6266666666666667,
    "SectionalFinalist": 0.35083333333333333,
    "StateQualifier": 0.15583333333333332,
    "StateFinalist": 0.06833333333333333,
    "StateChampion": 0.0325
  },
  {
    "Team": "Hillsboro",
    "Division": "5",
    "Region": "3A",
    "WIAASeed": 2,
    "BBMISeed": 20,
    "Seed": 2,
    "slug": "hillsboro",
    "RegionalSemis": 1.0,
    "RegionalChampion": 0.8966666666666666,
    "SectionalSemiFinalist": 0.6766666666666666,
    "SectionalFinalist": 0.3875,
    "StateQualifier": 0.12833333333333333,
    "StateFinalist": 0.050833333333333335,
    "StateChampion": 0.019166666666666665
  },
  {
    "Team": "Cochrane-Fountain City",
    "Division": "5",
    "Region": "3A",
    "WIAASeed": 3,
    "BBMISeed": 34,
    "Seed": 3,
    "slug": "cochrane-fountain-city",
    "RegionalSemis": 1.0,
    "RegionalChampion": 0.6191666666666666,
    "SectionalSemiFinalist": 0.1825,
    "SectionalFinalist": 0.08583333333333333,
    "StateQualifier": 0.01,
    "StateFinalist": 0.0033333333333333335,
    "StateChampion": 0.0008333333333333334
  },
  {
    "Team": "Assumption",
    "Division": "5",
    "Region": "3A",
    "WIAASeed": 4,
    "BBMISeed": 36,
    "Seed": 4,
    "slug": "assumption",
    "RegionalSemis": 1.0,
    "RegionalChampion": 0.7125,
    "SectionalSemiFinalist": 0.2675,
    "SectionalFinalist": 0.09333333333333334,
    "StateQualifier": 0.008333333333333333,
    "StateFinalist": 0.004166666666666667,
    "StateChampion": 0.0
  },
  {
    "Team": "Blair-Taylor",
    "Division": "5",
    "Region": "3A",
    "WIAASeed": 5,
    "BBMISeed": 58,
    "Seed": 5,
    "slug": "blair-taylor",
    "RegionalSemis": 1.0,
    "RegionalChampion": 0.2875,
    "SectionalSemiFinalist": 0.07333333333333333,
    "SectionalFinalist": 0.014166666666666666,
    "StateQualifier": 0.0016666666666666668,
    "StateFinalist": 0.0008333333333333334,
    "StateChampion": 0.0
  },
  {
    "Team": "Alma Center Lincoln",
    "Division": "5",
    "Region": "3A",
    "WIAASeed": 6,
    "BBMISeed": 43,
    "Seed": 6,
    "slug": "alma-center-lincoln",
    "RegionalSemis": 1.0,
    "RegionalChampion": 0.38083333333333336,
    "SectionalSemiFinalist": 0.10333333333333333,
    "SectionalFinalist": 0.04833333333333333,
    "StateQualifier": 0.0025,
    "StateFinalist": 0.0,
    "StateChampion": 0.0
  },
  {
    "Team": "Alma/Pepin",
    "Division": "5",
    "Region": "3A",
    "WIAASeed": 8,
    "BBMISeed": 59,
    "Seed": 8,
    "slug": "alma-pepin",
    "RegionalSemis": 1.0,
    "RegionalChampion": 0.08666666666666667,
    "SectionalSemiFinalist": 0.0325,
    "SectionalFinalist": 0.0075,
    "StateQualifier": 0.0,
    "StateFinalist": 0.0,
    "StateChampion": 0.0
  },
  {
    "Team": "Plum City/Elmwood",
    "Division": "5",
    "Region": "3A",
    "WIAASeed": 10,
    "BBMISeed": 74,
    "Seed": 7,
    "slug": "plum-city-elmwood",
    "RegionalSemis": 1.0,
    "RegionalChampion": 0.10333333333333333,
    "SectionalSemiFinalist": 0.0375,
    "SectionalFinalist": 0.0125,
    "StateQualifier": 0.0,
    "StateFinalist": 0.0,
    "StateChampion": 0.0
  },
  {
    "Team": "North Crawford",
    "Division": "5",
    "Region": "3B",
    "WIAASeed": 1,
    "BBMISeed": 5,
    "Seed": 1,
    "slug": "north-crawford",
    "RegionalSemis": 1.0,
    "RegionalChampion": 0.8866666666666667,
    "SectionalSemiFinalist": 0.5233333333333333,
    "SectionalFinalist": 0.2633333333333333,
    "StateQualifier": 0.19833333333333333,
    "StateFinalist": 0.12166666666666667,
    "StateChampion": 0.06166666666666667
  },
  {
    "Team": "Kickapoo",
    "Division": "5",
    "Region": "3B",
    "WIAASeed": 2,
    "BBMISeed": 3,
    "Seed": 2,
    "slug": "kickapoo",
    "RegionalSemis": 1.0,
    "RegionalChampion": 0.9008333333333334,
    "SectionalSemiFinalist": 0.7116666666666667,
    "SectionalFinalist": 0.4683333333333333,
    "StateQualifier": 0.32083333333333336,
    "StateFinalist": 0.20166666666666666,
    "StateChampion": 0.12416666666666666
  },
  {
    "Team": "Southwestern",
    "Division": "5",
    "Region": "3B",
    "WIAASeed": 3,
    "BBMISeed": 4,
    "Seed": 3,
    "slug": "southwestern",
    "RegionalSemis": 1.0,
    "RegionalChampion": 0.8525,
    "SectionalSemiFinalist": 0.24333333333333335,
    "SectionalFinalist": 0.16416666666666666,
    "StateQualifier": 0.115,
    "StateFinalist": 0.06583333333333333,
    "StateChampion": 0.0375
  },
  {
    "Team": "Belmont",
    "Division": "5",
    "Region": "3B",
    "WIAASeed": 4,
    "BBMISeed": 10,
    "Seed": 4,
    "slug": "belmont",
    "RegionalSemis": 1.0,
    "RegionalChampion": 0.7891666666666667,
    "SectionalSemiFinalist": 0.385,
    "SectionalFinalist": 0.08,
    "StateQualifier": 0.049166666666666664,
    "StateFinalist": 0.021666666666666667,
    "StateChampion": 0.009166666666666667
  },
  {
    "Team": "River Ridge",
    "Division": "5",
    "Region": "3B",
    "WIAASeed": 5,
    "BBMISeed": 21,
    "Seed": 5,
    "slug": "river-ridge",
    "RegionalSemis": 1.0,
    "RegionalChampion": 0.21083333333333334,
    "SectionalSemiFinalist": 0.07333333333333333,
    "SectionalFinalist": 0.01,
    "StateQualifier": 0.005,
    "StateFinalist": 0.0033333333333333335,
    "StateChampion": 0.0016666666666666668
  },
  {
    "Team": "De Soto",
    "Division": "5",
    "Region": "3B",
    "WIAASeed": 6,
    "BBMISeed": 35,
    "Seed": 6,
    "slug": "de-soto",
    "RegionalSemis": 1.0,
    "RegionalChampion": 0.1475,
    "SectionalSemiFinalist": 0.014166666666666666,
    "SectionalFinalist": 0.0033333333333333335,
    "StateQualifier": 0.0016666666666666668,
    "StateFinalist": 0.0,
    "StateChampion": 0.0
  },
  {
    "Team": "Potosi/Cassville",
    "Division": "5",
    "Region": "3B",
    "WIAASeed": 7,
    "BBMISeed": 25,
    "Seed": 7,
    "slug": "potosi-cassville",
    "RegionalSemis": 1.0,
    "RegionalChampion": 0.09916666666666667,
    "SectionalSemiFinalist": 0.030833333333333334,
    "SectionalFinalist": 0.010833333333333334,
    "StateQualifier": 0.0033333333333333335,
    "StateFinalist": 0.0016666666666666668,
    "StateChampion": 0.0
  },
  {
    "Team": "Seneca",
    "Division": "5",
    "Region": "3B",
    "WIAASeed": 8,
    "BBMISeed": 42,
    "Seed": 8,
    "slug": "seneca",
    "RegionalSemis": 1.0,
    "RegionalChampion": 0.11333333333333333,
    "SectionalSemiFinalist": 0.018333333333333333,
    "SectionalFinalist": 0.0,
    "StateQualifier": 0.0,
    "StateFinalist": 0.0,
    "StateChampion": 0.0
  },
  {
    "Team": "Abundant Life",
    "Division": "5",
    "Region": "4A",
    "WIAASeed": 1,
    "BBMISeed": 15,
    "Seed": 1,
    "slug": "abundant-life",
    "RegionalSemis": 1.0,
    "RegionalChampion": 0.9275,
    "SectionalSemiFinalist": 0.6316666666666667,
    "SectionalFinalist": 0.3408333333333333,
    "StateQualifier": 0.16,
    "StateFinalist": 0.07,
    "StateChampion": 0.0325
  },
  {
    "Team": "Barneveld",
    "Division": "5",
    "Region": "4A",
    "WIAASeed": 2,
    "BBMISeed": 14,
    "Seed": 2,
    "slug": "barneveld",
    "RegionalSemis": 1.0,
    "RegionalChampion": 0.8783333333333333,
    "SectionalSemiFinalist": 0.7425,
    "SectionalFinalist": 0.4775,
    "StateQualifier": 0.18916666666666668,
    "StateFinalist": 0.08083333333333333,
    "StateChampion": 0.03916666666666667
  },
  {
    "Team": "Saint Ambrose",
    "Division": "5",
    "Region": "4A",
    "WIAASeed": 3,
    "BBMISeed": 24,
    "Seed": 3,
    "slug": "saint-ambrose",
    "RegionalSemis": 1.0,
    "RegionalChampion": 0.6908333333333333,
    "SectionalSemiFinalist": 0.14916666666666667,
    "SectionalFinalist": 0.0825,
    "StateQualifier": 0.0175,
    "StateFinalist": 0.0016666666666666668,
    "StateChampion": 0.0
  },
  {
    "Team": "Johnson Creek",
    "Division": "5",
    "Region": "4A",
    "WIAASeed": 5,
    "BBMISeed": 37,
    "Seed": 5,
    "slug": "johnson-creek",
    "RegionalSemis": 1.0,
    "RegionalChampion": 0.475,
    "SectionalSemiFinalist": 0.19333333333333333,
    "SectionalFinalist": 0.03333333333333333,
    "StateQualifier": 0.006666666666666667,
    "StateFinalist": 0.0025,
    "StateChampion": 0.0
  },
  {
    "Team": "Randolph",
    "Division": "5",
    "Region": "4A",
    "WIAASeed": 6,
    "BBMISeed": 39,
    "Seed": 6,
    "slug": "randolph",
    "RegionalSemis": 1.0,
    "RegionalChampion": 0.30916666666666665,
    "SectionalSemiFinalist": 0.05583333333333333,
    "SectionalFinalist": 0.025,
    "StateQualifier": 0.005,
    "StateFinalist": 0.0033333333333333335,
    "StateChampion": 0.0
  },
  {
    "Team": "Fall River",
    "Division": "5",
    "Region": "4A",
    "WIAASeed": 7,
    "BBMISeed": 40,
    "Seed": 7,
    "slug": "fall-river",
    "RegionalSemis": 1.0,
    "RegionalChampion": 0.12166666666666667,
    "SectionalSemiFinalist": 0.0525,
    "SectionalFinalist": 0.02,
    "StateQualifier": 0.0033333333333333335,
    "StateFinalist": 0.0008333333333333334,
    "StateChampion": 0.0008333333333333334
  },
  {
    "Team": "Madison Country Day",
    "Division": "5",
    "Region": "4A",
    "WIAASeed": 9,
    "BBMISeed": 84,
    "Seed": 8,
    "slug": "madison-country-day",
    "RegionalSemis": 1.0,
    "RegionalChampion": 0.0725,
    "SectionalSemiFinalist": 0.016666666666666666,
    "SectionalFinalist": 0.0016666666666666668,
    "StateQualifier": 0.0,
    "StateFinalist": 0.0,
    "StateChampion": 0.0
  },
  {
    "Team": "Rio",
    "Division": "5",
    "Region": "4A",
    "WIAASeed": 13,
    "BBMISeed": 52,
    "Seed": 4,
    "slug": "rio",
    "RegionalSemis": 1.0,
    "RegionalChampion": 0.525,
    "SectionalSemiFinalist": 0.15833333333333333,
    "SectionalFinalist": 0.019166666666666665,
    "StateQualifier": 0.0,
    "StateFinalist": 0.0,
    "StateChampion": 0.0
  },
  {
    "Team": "Oakfield",
    "Division": "5",
    "Region": "4B",
    "WIAASeed": 1,
    "BBMISeed": 7,
    "Seed": 1,
    "slug": "oakfield",
    "RegionalSemis": 1.0,
    "RegionalChampion": 0.9266666666666666,
    "SectionalSemiFinalist": 0.6333333333333333,
    "SectionalFinalist": 0.31666666666666665,
    "StateQualifier": 0.21,
    "StateFinalist": 0.11,
    "StateChampion": 0.049166666666666664
  },
  {
    "Team": "Sheboygan Lutheran",
    "Division": "5",
    "Region": "4B",
    "WIAASeed": 2,
    "BBMISeed": 6,
    "Seed": 2,
    "slug": "sheboygan-lutheran",
    "RegionalSemis": 1.0,
    "RegionalChampion": 0.9375,
    "SectionalSemiFinalist": 0.7258333333333333,
    "SectionalFinalist": 0.4708333333333333,
    "StateQualifier": 0.2991666666666667,
    "StateFinalist": 0.15,
    "StateChampion": 0.09
  },
  {
    "Team": "Chesterton Academy Milwaukee",
    "Division": "5",
    "Region": "4B",
    "WIAASeed": 3,
    "BBMISeed": 13,
    "Seed": 3,
    "slug": "chesterton-academy-milwaukee",
    "RegionalSemis": 1.0,
    "RegionalChampion": 0.9158333333333334,
    "SectionalSemiFinalist": 0.25,
    "SectionalFinalist": 0.15166666666666667,
    "StateQualifier": 0.08666666666666667,
    "StateFinalist": 0.03833333333333333,
    "StateChampion": 0.0175
  },
  {
    "Team": "Central Wisconsin Christian",
    "Division": "5",
    "Region": "4B",
    "WIAASeed": 4,
    "BBMISeed": 30,
    "Seed": 4,
    "slug": "central-wisconsin-christian",
    "RegionalSemis": 1.0,
    "RegionalChampion": 0.7383333333333333,
    "SectionalSemiFinalist": 0.26916666666666667,
    "SectionalFinalist": 0.04583333333333333,
    "StateQualifier": 0.020833333333333332,
    "StateFinalist": 0.0075,
    "StateChampion": 0.0008333333333333334
  },
  {
    "Team": "Palmyra-Eagle",
    "Division": "5",
    "Region": "4B",
    "WIAASeed": 5,
    "BBMISeed": 47,
    "Seed": 5,
    "slug": "palmyra-eagle",
    "RegionalSemis": 1.0,
    "RegionalChampion": 0.26166666666666666,
    "SectionalSemiFinalist": 0.08416666666666667,
    "SectionalFinalist": 0.009166666666666667,
    "StateQualifier": 0.0008333333333333334,
    "StateFinalist": 0.0,
    "StateChampion": 0.0
  },
  {
    "Team": "Faith Christian",
    "Division": "5",
    "Region": "4B",
    "WIAASeed": 6,
    "BBMISeed": 48,
    "Seed": 6,
    "slug": "faith-christian",
    "RegionalSemis": 1.0,
    "RegionalChampion": 0.08416666666666667,
    "SectionalSemiFinalist": 0.013333333333333334,
    "SectionalFinalist": 0.0025,
    "StateQualifier": 0.0,
    "StateFinalist": 0.0,
    "StateChampion": 0.0
  },
  {
    "Team": "Lake Country Classical Academy",
    "Division": "5",
    "Region": "4B",
    "WIAASeed": 7,
    "BBMISeed": 70,
    "Seed": 7,
    "slug": "lake-country-classical-academy",
    "RegionalSemis": 1.0,
    "RegionalChampion": 0.0625,
    "SectionalSemiFinalist": 0.010833333333333334,
    "SectionalFinalist": 0.0025,
    "StateQualifier": 0.0008333333333333334,
    "StateFinalist": 0.0,
    "StateChampion": 0.0
  },
  {
    "Team": "Catholic Central",
    "Division": "5",
    "Region": "4B",
    "WIAASeed": 9,
    "BBMISeed": 62,
    "Seed": 8,
    "slug": "catholic-central",
    "RegionalSemis": 1.0,
    "RegionalChampion": 0.07333333333333333,
    "SectionalSemiFinalist": 0.013333333333333334,
    "SectionalFinalist": 0.0008333333333333334,
    "StateQualifier": 0.0,
    "StateFinalist": 0.0,
    "StateChampion": 0.0
  }
]